certbot_dns_varo/__init__.py
certbot_dns_varo/dns_varo.py
certbot_dns_varo-1.0.0.dist-info/METADATA
certbot_dns_varo-1.0.0.dist-info/WHEEL
certbot_dns_varo-1.0.0.dist-info/entry_points.txt
certbot_dns_varo-1.0.0.dist-info/top_level.txt
certbot_dns_varo-1.0.0.dist-info/RECORD
