Metadata-Version: 2.1
Name: certbot-dns-varo
Version: 1.0.0
Summary: A Certbot plugin for Varo
Home-page: https://github.com/varodomains/certbot-dns-varo
Author: eskimo
Author-email: me@eskimo.dev
License: MIT
Classifier: Development Status :: 3 - Alpha
Classifier: Intended Audience :: Developers
Classifier: Topic :: Internet :: WWW/HTTP
Classifier: License :: OSI Approved :: MIT License
Classifier: Programming Language :: Python :: 3
Requires-Dist: certbot
Requires-Dist: requests
Requires-Dist: zope.interface
